fastapi_mock_middleware/__init__.py
fastapi_mock_middleware/middleware.py
fastapi_mock_middleware-0.1.1.dist-info/LICENSE.txt
fastapi_mock_middleware-0.1.1.dist-info/METADATA
fastapi_mock_middleware-0.1.1.dist-info/WHEEL
fastapi_mock_middleware-0.1.1.dist-info/top_level.txt
fastapi_mock_middleware-0.1.1.dist-info/RECORD
