Metadata-Version: 2.1
Name: fastapi-mock-middleware
Version: 0.1.1
Summary: FastAPI middleware for mocking response data of non-implemented endpoints
Author-email: Niyaz Batyrshin <Niyaz.Batyrshin@gmail.com>
License: MIT License
Project-URL: homepage, https://NiyazNz.github.io/fastapi-mock-middleware
Project-URL: repository, https://github.com/NiyazNz/fastapi-mock-middleware.git
Project-URL: issues, https://github.com/NiyazNz/fastapi-mock-middleware/issues
Keywords: fastapi,mock,mock API,mock fastapi,mock response,API first
Classifier: Programming Language :: Python :: 3
Classifier: License :: OSI Approved :: MIT License
Classifier: Operating System :: OS Independent
Requires-Python: >=3.8
License-File: LICENSE.txt
Requires-Dist: fastapi >=0.103.0
Requires-Dist: polyfactory >=2.8.0
Provides-Extra: dev
Requires-Dist: uvicorn ; extra == 'dev'
Requires-Dist: ipython ; extra == 'dev'
Provides-Extra: test
Requires-Dist: pytest ; extra == 'test'
Requires-Dist: pytest-asyncio ; extra == 'test'
Requires-Dist: pytest-cov ; extra == 'test'
Requires-Dist: flake8 ; extra == 'test'
Requires-Dist: httpx ; extra == 'test'
